langswarm_memory/__init__.py
langswarm_memory/agent_memory_impl.py
langswarm_memory/agent_memory_interfaces.py
langswarm_memory/agent_memory_types.py
langswarm_memory/backends.py
langswarm_memory/base.py
langswarm_memory/errors.py
langswarm_memory/factory.py
langswarm_memory/interfaces.py
langswarm_memory/memory_enhancements.py
langswarm_memory/utils.py
langswarm_memory/vector_backend.py
langswarm_memory/reflexive/__init__.py
langswarm_memory/reflexive/consolidator.py
langswarm_memory/reflexive/models.py
langswarm_memory/reflexive/reflector.py
langswarm_memory/reflexive/retriever.py
langswarm_memory/reflexive/store.py
langswarm_memory/vector_stores/__init__.py
langswarm_memory/vector_stores/chroma_native.py
langswarm_memory/vector_stores/factory.py
langswarm_memory/vector_stores/interfaces.py
langswarm_memory/vector_stores/pgvector_native.py
langswarm_memory/vector_stores/pinecone_native.py
langswarm_memory/vector_stores/qdrant_native.py
langswarm_memory/vector_stores/redis_native.py
langswarm_memory/vector_stores/sqlite_native.py
langswarm_memory-0.2.0.dist-info/licenses/LICENSE
langswarm_memory-0.2.0.dist-info/METADATA
langswarm_memory-0.2.0.dist-info/WHEEL
langswarm_memory-0.2.0.dist-info/top_level.txt
langswarm_memory-0.2.0.dist-info/RECORD
