Metadata-Version: 2.4
Name: langswarm-memory
Version: 0.2.0
Summary: Enterprise-grade conversational memory for AI agents
Author-email: Alexander Ekdahl <alexander.ekdahl@gmail.com>
License: Apache-2.0
Project-URL: Homepage, https://github.com/aekdahl/langswarm
Project-URL: Documentation, https://github.com/aekdahl/langswarm#readme
Project-URL: Repository, https://github.com/aekdahl/langswarm
Project-URL: Issues, https://github.com/aekdahl/langswarm/issues
Keywords: AI,agents,memory,conversation,LLM,chatbot
Classifier: Development Status :: 3 - Alpha
Classifier: Intended Audience :: Developers
Classifier: License :: OSI Approved :: Apache Software License
Classifier: Programming Language :: Python :: 3
Classifier: Programming Language :: Python :: 3.8
Classifier: Programming Language :: Python :: 3.9
Classifier: Programming Language :: Python :: 3.10
Classifier: Programming Language :: Python :: 3.11
Classifier: Programming Language :: Python :: 3.12
Classifier: Topic :: Software Development :: Libraries :: Python Modules
Classifier: Topic :: Scientific/Engineering :: Artificial Intelligence
Requires-Python: >=3.8
License-File: LICENSE
Requires-Dist: pyyaml>=6.0
Provides-Extra: redis
Requires-Dist: redis>=4.0.0; extra == "redis"
Provides-Extra: bigquery
Requires-Dist: google-cloud-bigquery>=3.0.0; extra == "bigquery"
Provides-Extra: postgres
Requires-Dist: asyncpg>=0.27.0; extra == "postgres"
Requires-Dist: pgvector>=0.2.0; extra == "postgres"
Provides-Extra: mongodb
Requires-Dist: motor>=3.0.0; extra == "mongodb"
Provides-Extra: elasticsearch
Requires-Dist: elasticsearch[async]>=8.0.0; extra == "elasticsearch"
Provides-Extra: vector
Requires-Dist: numpy>=1.20.0; extra == "vector"
Provides-Extra: chromadb
Requires-Dist: chromadb>=0.4.0; extra == "chromadb"
Provides-Extra: qdrant
Requires-Dist: qdrant-client>=1.0.0; extra == "qdrant"
Provides-Extra: pinecone
Requires-Dist: pinecone-client>=2.0.0; extra == "pinecone"
Provides-Extra: all-backends
Requires-Dist: redis>=4.0.0; extra == "all-backends"
Requires-Dist: google-cloud-bigquery>=3.0.0; extra == "all-backends"
Requires-Dist: asyncpg>=0.27.0; extra == "all-backends"
Requires-Dist: pgvector>=0.2.0; extra == "all-backends"
Requires-Dist: motor>=3.0.0; extra == "all-backends"
Requires-Dist: elasticsearch[async]>=8.0.0; extra == "all-backends"
Provides-Extra: all-vector
Requires-Dist: numpy>=1.20.0; extra == "all-vector"
Requires-Dist: chromadb>=0.4.0; extra == "all-vector"
Requires-Dist: qdrant-client>=1.0.0; extra == "all-vector"
Requires-Dist: pinecone-client>=2.0.0; extra == "all-vector"
Provides-Extra: all
Requires-Dist: redis>=4.0.0; extra == "all"
Requires-Dist: google-cloud-bigquery>=3.0.0; extra == "all"
Requires-Dist: asyncpg>=0.27.0; extra == "all"
Requires-Dist: pgvector>=0.2.0; extra == "all"
Requires-Dist: motor>=3.0.0; extra == "all"
Requires-Dist: elasticsearch[async]>=8.0.0; extra == "all"
Requires-Dist: numpy>=1.20.0; extra == "all"
Requires-Dist: chromadb>=0.4.0; extra == "all"
Requires-Dist: qdrant-client>=1.0.0; extra == "all"
Requires-Dist: pinecone-client>=2.0.0; extra == "all"
Provides-Extra: dev
Requires-Dist: pytest>=7.0; extra == "dev"
Requires-Dist: pytest-asyncio>=0.21; extra == "dev"
Requires-Dist: black; extra == "dev"
Requires-Dist: mypy; extra == "dev"
Requires-Dist: twine; extra == "dev"
Requires-Dist: build; extra == "dev"
Dynamic: license-file
